example_pkg/__init__.py
example_pkg_gunhoon-0.0.0.dist-info/LICENSE
example_pkg_gunhoon-0.0.0.dist-info/METADATA
example_pkg_gunhoon-0.0.0.dist-info/WHEEL
example_pkg_gunhoon-0.0.0.dist-info/top_level.txt
example_pkg_gunhoon-0.0.0.dist-info/RECORD
