Metadata-Version: 2.1
Name: example-pkg-gunhoon
Version: 0.0.0
Summary: A small example package
Home-page: https://github.com/gunhoon/packaging-tutorial
Author: Gunhoon Lee
Author-email: gunhoon@gmail.com
Project-URL: Bug Tracker, https://github.com/gunhoon/packaging-tutorial/issues
Classifier: Programming Language :: Python :: 3
Classifier: License :: OSI Approved :: MIT License
Classifier: Operating System :: OS Independent
Requires-Python: >=3.6
License-File: LICENSE
